model_template/__init__.py
model_template/model_template.py
model_template-197757727.dist-info/METADATA
model_template-197757727.dist-info/WHEEL
model_template-197757727.dist-info/top_level.txt
model_template-197757727.dist-info/RECORD
