Metadata-Version: 2.1
Name: model-template
Version: 197757727
Summary: A abstract Template class for running multiples machine                    learning models in the same system.
Home-page: https://gitlab.com/bumbleblo/modeltemplate
Author: Felipe Borges
Author-email: bumbleblo2013@gmail.com
License: MIT
Platform: UNKNOWN
